aesplot/__init__.py
aesplot/Framework/__init__.py
aesplot/utils/__init__.py
aesplot/utils/latex_to_html.py
aesplot/utils/svg_text_fix.py
aesplot-1.1.dist-info/LICENSE
aesplot-1.1.dist-info/METADATA
aesplot-1.1.dist-info/WHEEL
aesplot-1.1.dist-info/top_level.txt
aesplot-1.1.dist-info/RECORD
