Metadata-Version: 2.1
Name: aesplot
Version: 1.1
Summary: Aesthetics and Framework
Author: Heitor Gessner
Author-email: <lab.metabio@gmail.com>
Project-URL: Source, https://github.com/hmynssen/Aesplot
Keywords: R,statistics,latex,html,aesthetics
Classifier: Development Status :: 4 - Beta
Classifier: Programming Language :: Python :: 3
Classifier: Operating System :: MacOS
Classifier: Operating System :: Microsoft :: Windows
Classifier: Operating System :: Unix
Requires-Python: >=3.0, <4
License-File: LICENSE
Requires-Dist: numpy
Requires-Dist: matplotlib
Requires-Dist: scipy
Requires-Dist: pandas
